{
  "title": "작업 사례",
  "subtitle": "실제 고객 인쇄물을 확인하세요",
  "client": "포트폴리오",
  "category": "digital-strategy",
  "year": 2025,
  "image": "/src/assets/works/portfolio.jpg",
  "description": "다양한 업종의 고객사와 함께한 인쇄 작업 사례를 소개합니다.",
  "overview": "Sungjinprint는 기업 카탈로그, 학교 졸업앨범, 단체 책자 등 다양한 인쇄물을 제작해왔습니다. 고객의 요구에 맞춘 맞춤 상담과 꼼꼼한 작업으로 만족도 높은 결과물을 제공합니다.",
  "support": [
    "기업 카탈로그",
    "회사 소개서",
    "학교 졸업앨범",
    "단체 책자",
    "세미나 자료집"
  ],
  "achievements": [
    {
      "title": "기업 카탈로그",
      "description": "제품 사진이 선명하게 나오도록 아트지 + 유광 코팅으로 제작. 500부 주문, 3일 납기."
    },
    {
      "title": "학교 졸업앨범",
      "description": "스노우지 200g + 무선제본으로 고급스럽게 제작. 300부 주문, 5일 납기."
    },
    {
      "title": "세미나 자료집",
      "description": "모조지 80g + 중철제본으로 가볍게 제작. 200부 주문, 당일 출고."
    },
    {
      "title": "회사 소개서",
      "description": "스노우지 250g + 무광 코팅 + 금박으로 프리미엄 제작. 100부 주문, 5일 납기."
    }
  ]
}
